{"nodes": [{"id": "c_users_razielescamilla_gestiondeinventario_mcp_json", "label": ".mcp.json", "file_type": "code", "source_file": "C:\\Users\\RazielEscamilla\\Gestiondeinventario\\.mcp.json", "source_location": "L1"}, {"id": "gestiondeinventario_mcp_mcpservers", "label": "mcpServers", "file_type": "code", "source_file": "C:\\Users\\RazielEscamilla\\Gestiondeinventario\\.mcp.json", "source_location": "L2"}, {"id": "gestiondeinventario_mcp_mcpservers_ruflo", "label": "ruflo", "file_type": "code", "source_file": "C:\\Users\\RazielEscamilla\\Gestiondeinventario\\.mcp.json", "source_location": "L3"}, {"id": "gestiondeinventario_mcp_ruflo_command", "label": "command", "file_type": "code", "source_file": "C:\\Users\\RazielEscamilla\\Gestiondeinventario\\.mcp.json", "source_location": "L4"}, {"id": "gestiondeinventario_mcp_ruflo_args", "label": "args", "file_type": "code", "source_file": "C:\\Users\\RazielEscamilla\\Gestiondeinventario\\.mcp.json", "source_location": "L5"}], "edges": [{"source": "c_users_razielescamilla_gestiondeinventario_mcp_json", "target": "gestiondeinventario_mcp_mcpservers", "relation": "contains", "confidence": "EXTRACTED", "source_file": "C:\\Users\\RazielEscamilla\\Gestiondeinventario\\.mcp.json", "source_location": "L2", "weight": 1.0}, {"source": "gestiondeinventario_mcp_mcpservers", "target": "gestiondeinventario_mcp_mcpservers_ruflo", "relation": "contains", "confidence": "EXTRACTED", "source_file": "C:\\Users\\RazielEscamilla\\Gestiondeinventario\\.mcp.json", "source_location": "L3", "weight": 1.0}, {"source": "gestiondeinventario_mcp_mcpservers_ruflo", "target": "gestiondeinventario_mcp_ruflo_command", "relation": "contains", "confidence": "EXTRACTED", "source_file": "C:\\Users\\RazielEscamilla\\Gestiondeinventario\\.mcp.json", "source_location": "L4", "weight": 1.0}, {"source": "gestiondeinventario_mcp_mcpservers_ruflo", "target": "gestiondeinventario_mcp_ruflo_args", "relation": "contains", "confidence": "EXTRACTED", "source_file": "C:\\Users\\RazielEscamilla\\Gestiondeinventario\\.mcp.json", "source_location": "L5", "weight": 1.0}, {"source": "gestiondeinventario_mcp_ruflo_args", "target": "ref_ruflo_latest", "relation": "extends", "confidence": "EXTRACTED", "source_file": "C:\\Users\\RazielEscamilla\\Gestiondeinventario\\.mcp.json", "source_location": "L5", "weight": 1.0, "context": "import"}, {"source": "gestiondeinventario_mcp_ruflo_args", "target": "ref_mcp", "relation": "extends", "confidence": "EXTRACTED", "source_file": "C:\\Users\\RazielEscamilla\\Gestiondeinventario\\.mcp.json", "source_location": "L5", "weight": 1.0, "context": "import"}, {"source": "gestiondeinventario_mcp_ruflo_args", "target": "ref_start", "relation": "extends", "confidence": "EXTRACTED", "source_file": "C:\\Users\\RazielEscamilla\\Gestiondeinventario\\.mcp.json", "source_location": "L5", "weight": 1.0, "context": "import"}]}